bipsea/__init__.py
bipsea/bip32.py
bipsea/bip32types.py
bipsea/bip39.py
bipsea/bip85.py
bipsea/bipsea.py
bipsea/util.py
bipsea/wordlists/__init__.py
bipsea/wordlists/chinese_simplified.txt
bipsea/wordlists/chinese_traditional.txt
bipsea/wordlists/czech.txt
bipsea/wordlists/english.txt
bipsea/wordlists/french.txt
bipsea/wordlists/italian.txt
bipsea/wordlists/japanese.txt
bipsea/wordlists/korean.txt
bipsea/wordlists/portuguese.txt
bipsea/wordlists/spanish.txt
bipsea-3.0.0.dist-info/LICENSE.md
bipsea-3.0.0.dist-info/METADATA
bipsea-3.0.0.dist-info/WHEEL
bipsea-3.0.0.dist-info/entry_points.txt
bipsea-3.0.0.dist-info/RECORD
