Metadata-Version: 2.1
Name: bipsea
Version: 3.0.0
Summary: Composable Python CLI for Bitcoin mnemonics and BIP-85 secrets.
Home-page: https://github.com/akarve/bipsea
License: Apache-2.0
Keywords: Bitcoin,BIP-32,BIP-39,BIP-85,cryptography,secrets,ECDSA,entropy
Author: Aneesh Karve
Author-email: bonded_metals_0u@icloud.com
Requires-Python: >=3.8.1,<4.0
Classifier: Development Status :: 4 - Beta
Classifier: Intended Audience :: Developers
Classifier: License :: OSI Approved :: Apache Software License
Classifier: Programming Language :: Python :: 3
Classifier: Programming Language :: Python :: 3.9
Classifier: Programming Language :: Python :: 3.10
Classifier: Programming Language :: Python :: 3.11
Classifier: Programming Language :: Python :: 3.12
Classifier: Programming Language :: Python :: 3.8
Classifier: Topic :: Security :: Cryptography
Classifier: Topic :: Software Development :: Libraries
Classifier: Topic :: Utilities
Requires-Dist: base58 (>=2.1.1,<2.2.0)
Requires-Dist: build (>=1.2.1,<1.3.0)
Requires-Dist: click (>=8.1.3,<8.2.0)
Requires-Dist: ecdsa (>=0.19.0,<0.20.0)
Project-URL: Repository, https://github.com/akarve/bipsea
